r_scripts/__init__.py
r_scripts/ada_cross_validation.R
r_scripts/ada_model_builder.R
r_scripts/ada_model_builder_ntChange.R
r_scripts/ada_model_predictor.R
r_scripts/xgboost_model_builder_ntChange.R
r_scripts/xgboost_model_predictor.R
somaticseq/SSeq_tsv2vcf.py
somaticseq/__init__.py
somaticseq/_version.py
somaticseq/annotate_caller.py
somaticseq/bam_features.py
somaticseq/combine_callers.py
somaticseq/defaults.py
somaticseq/ntchange_type.py
somaticseq/run_somaticseq.py
somaticseq/sequencing_features.py
somaticseq/single_sample_vcf2tsv.py
somaticseq/somatic_tsv2vcf.py
somaticseq/somatic_vcf2tsv.py
somaticseq/somatic_xgboost.py
somaticseq/somaticseq_parallel.py
somaticseq/tsv2vcf.py
somaticseq/genomicFileHandler/__init__.py
somaticseq/genomicFileHandler/concat.py
somaticseq/genomicFileHandler/genomic_file_handlers.py
somaticseq/genomicFileHandler/pileup_reader.py
somaticseq/genomicFileHandler/read_info_extractor.py
somaticseq/genomic_file_parsers/__init__.py
somaticseq/genomic_file_parsers/concat.py
somaticseq/genomic_file_parsers/genomic_file_handlers.py
somaticseq/genomic_file_parsers/pileup_reader.py
somaticseq/genomic_file_parsers/read_info_extractor.py
somaticseq/utilities/BAM_filter.py
somaticseq/utilities/README.md
somaticseq/utilities/__init__.py
somaticseq/utilities/attach_pileupVAF.py
somaticseq/utilities/bamQC.py
somaticseq/utilities/bedFileHandler.py
somaticseq/utilities/combo_callers_evaluator.py
somaticseq/utilities/filter_SomaticSeq_VCF.py
somaticseq/utilities/linguistic_sequence_complexity.py
somaticseq/utilities/lociCounterWithLabels.py
somaticseq/utilities/lociCounters.py
somaticseq/utilities/multi-nucleotide_phaser.py
somaticseq/utilities/paired_end_bam2fastq.py
somaticseq/utilities/plot_TPvsFP.py
somaticseq/utilities/reformat_VCF2SEQC2.py
somaticseq/utilities/remove_callers_from_somaticseq_tsv.py
somaticseq/utilities/split_Bed_into_equal_regions.py
somaticseq/utilities/split_bed_into_equal_regions.py
somaticseq/utilities/split_mergedBed.py
somaticseq-3.11.1.dist-info/LICENSE.txt
somaticseq-3.11.1.dist-info/METADATA
somaticseq-3.11.1.dist-info/WHEEL
somaticseq-3.11.1.dist-info/entry_points.txt
somaticseq-3.11.1.dist-info/top_level.txt
somaticseq-3.11.1.dist-info/RECORD
