Metadata-Version: 2.1
Name: somaticseq
Version: 3.11.1
Summary: SomaticSeq: An ensemble approach to accurately detect somatic mutations using SomaticSeq
Home-page: https://github.com/bioinform/somaticseq
Author: Li Tai Fang, Pegah Tootoonchi Afshar, Aparna Chhibber, Marghoob Mohiyuddin, John C. Mu, Greg Gibeling, Sharon Barr, Narges Bani Asadi, Hugo Y.K. Lam
Author-email: ltfang@gmail.com
Maintainer-email: Li Tai Fang <ltfang@gmail.com>
License: BSD-2-Clause
Project-URL: Homepage, https://github.com/bioinform/somaticseq
Keywords: somatic mutations,bioinformatics,genomics,ngs
Classifier: Development Status :: 5 - Production/Stable
Classifier: Topic :: Scientific/Engineering :: Bio-Informatics
Classifier: Intended Audience :: Science/Research
Classifier: Intended Audience :: Healthcare Industry
Classifier: Programming Language :: Python :: 3
Requires-Python: >=3.11.0
License-File: LICENSE.txt
Requires-Dist: pysam
Requires-Dist: numpy
Requires-Dist: scipy
Requires-Dist: pandas
Requires-Dist: pybedtools>=0.12.0
Requires-Dist: xgboost>=1.4
Requires-Dist: pydantic<3.0,>=2.0.0
Provides-Extra: dev
Requires-Dist: black; extra == "dev"
Requires-Dist: flake8; extra == "dev"
Requires-Dist: mypy; extra == "dev"
Requires-Dist: pytest; extra == "dev"
Requires-Dist: pytest-mock; extra == "dev"
Requires-Dist: twine; extra == "dev"
